{
  "name": "Einwirkung",
  "type": "miracle",
  "img": "icons/svg/book.svg",
  "system": {
    "description": "Erlaubt das dauerhafte Binden eines Wunders bis Stufe 3 zu den jeweiligen MP-Kosten pro Anwendung.",
    "list": "Wunder (Leitmagie)",
    "rank": 8,
    "cost": 3,
    "costOptions": [
      3
    ],
    "range": "Berührung",
    "targeted": false,
    "duration": "",
    "sourcePage": 45,
    "sourcePdf": "ABOREA-1-Spielerheft-6ED.pdf",
    "slug": "einwirkung",
    "externalId": "wunder-leitmagie--einwirkung--8",
    "domain": "Wunder (Leitmagie)"
  },
  "_id": "0b4a51796e0e41c6",
  "folder": null,
  "flags": {},
  "ownership": {
    "default": 0
  }
}