{
  "name": "Dauerhaftes Zeichen",
  "type": "miracle",
  "img": "icons/svg/book.svg",
  "system": {
    "description": "Markiert einen Ort/Gegenstand dauerhaft mit einem Spruch bis Rang 4. Jede Auslösung/1 MP.",
    "list": "Zeichen (Leitmagie)",
    "rank": 5,
    "cost": 1,
    "costOptions": [
      1,
      4
    ],
    "range": "Berührung",
    "targeted": false,
    "duration": "",
    "sourcePage": 45,
    "sourcePdf": "ABOREA-1-Spielerheft-6ED.pdf",
    "slug": "dauerhaftes-zeichen",
    "externalId": "zeichen-leitmagie--dauerhaftes-zeichen--5",
    "domain": "Zeichen (Leitmagie)"
  },
  "_id": "3acaedf666ce7306",
  "flags": {
    "aborea-v7": {
      "sourceId": "zeichen-leitmagie--dauerhaftes-zeichen--5",
      "sourcePath": "systems/aborea-v7/packs/miracles/_source/zeichen-leitmagie--dauerhaftes-zeichen--5.json",
      "generated": true
    }
  },
  "ownership": {
    "default": 0
  },
  "folder": null
}